mpl_colr2svg/__init__.py
mpl_colr2svg/_version.py
mpl_colr2svg/color_emoji.py
mpl_colr2svg/color_emoji_blackrenderer.py
mpl_colr2svg/colr2svg.py
mpl_colr2svg/patch_nanoemoji.py
mpl_colr2svg/tests/__init__.py
mpl_colr2svg/tests/test_example.py
mpl_colr2svg-0.1.0.dist-info/LICENSE
mpl_colr2svg-0.1.0.dist-info/LICENSE_old
mpl_colr2svg-0.1.0.dist-info/METADATA
mpl_colr2svg-0.1.0.dist-info/WHEEL
mpl_colr2svg-0.1.0.dist-info/top_level.txt
mpl_colr2svg-0.1.0.dist-info/RECORD
